pollination/point_in_time_view/__init__.py
pollination/point_in_time_view/_prepare_folder.py
pollination/point_in_time_view/_raytracing.py
pollination/point_in_time_view/entry.py
pollination_point_in_time_view-0.5.0.dist-info/LICENSE
pollination_point_in_time_view-0.5.0.dist-info/METADATA
pollination_point_in_time_view-0.5.0.dist-info/WHEEL
pollination_point_in_time_view-0.5.0.dist-info/top_level.txt
pollination_point_in_time_view-0.5.0.dist-info/RECORD
