Metadata-Version: 2.1
Name: pollination-point-in-time-view
Version: 0.5.0
Summary: Point-in-time view-based recipe for Pollination.
Home-page: https://github.com/pollination/point-in-time-view
Author: ladybug-tools
Author-email: info@ladybug.tools
Maintainer: chris, ladybug-tools
Maintainer-email: chris@ladybug.tools, info@ladybug.tools
License: PolyForm Shield License 1.0.0, https://polyformproject.org/wp-content/uploads/2020/06/PolyForm-Shield-1.0.0.txt
Project-URL: icon, https://raw.githubusercontent.com/ladybug-tools/artwork/master/icons_components/honeybee/png/viewrecipe.png
Project-URL: docker, https://hub.docker.com/r/ladybugtools/honeybee-radiance
Keywords: honeybee,radiance,ladybug-tools,illuminance,irradiance,point-in-time-view
License-File: LICENSE
Requires-Dist: pollination-honeybee-radiance>=0.22.73
Requires-Dist: pollination-alias>=0.11.8
